envmodules.py
envmodules-0.1.dist-info/LICENSE
envmodules-0.1.dist-info/WHEEL
envmodules-0.1.dist-info/METADATA
envmodules-0.1.dist-info/RECORD
