Metadata-Version: 2.1
Name: envmodules
Version: 0.1
Summary: Python wrapper around environment modules ("module load")
Home-page: https://github.com/European-XFEL/envmodules
License: UNKNOWN
Author: European XFEL GmbH
Author-email: da-support@xfel.eu
Classifier: License :: OSI Approved :: BSD License
